odoo10_addon_website_container_fluid-10.0.1.0.0-py2.7-nspkg.pth
odoo/addons/website_container_fluid/README.rst
odoo/addons/website_container_fluid/__init__.py
odoo/addons/website_container_fluid/__manifest__.py
odoo/addons/website_container_fluid/demo/pages.xml
odoo/addons/website_container_fluid/i18n/bg.po
odoo/addons/website_container_fluid/i18n/de.po
odoo/addons/website_container_fluid/i18n/el_GR.po
odoo/addons/website_container_fluid/i18n/es.po
odoo/addons/website_container_fluid/i18n/fr.po
odoo/addons/website_container_fluid/i18n/it.po
odoo/addons/website_container_fluid/i18n/pt_BR.po
odoo/addons/website_container_fluid/i18n/ru.po
odoo/addons/website_container_fluid/i18n/sl.po
odoo/addons/website_container_fluid/static/description/icon.png
odoo/addons/website_container_fluid/templates/snippets.xml
odoo10_addon_website_container_fluid-10.0.1.0.0.dist-info/DESCRIPTION.rst
odoo10_addon_website_container_fluid-10.0.1.0.0.dist-info/METADATA
odoo10_addon_website_container_fluid-10.0.1.0.0.dist-info/RECORD
odoo10_addon_website_container_fluid-10.0.1.0.0.dist-info/WHEEL
odoo10_addon_website_container_fluid-10.0.1.0.0.dist-info/metadata.json
odoo10_addon_website_container_fluid-10.0.1.0.0.dist-info/namespace_packages.txt
odoo10_addon_website_container_fluid-10.0.1.0.0.dist-info/top_level.txt
