Metadata-Version: 2.0
Name: odoo10-addon-website-container-fluid
Version: 10.0.1.0.0
Summary: Let you choose between fixed or fluid containers
Home-page: https://www.tecnativa.com
Author: Grupo ESOC Ingeniería de Servicios, Tecnativa, Odoo Community Association (OCA)
Author-email: support@odoo-community.org
License: LGPL-3
Platform: UNKNOWN
Classifier: Programming Language :: Python :: 2.7
Classifier: Framework :: Odoo
Classifier: License :: OSI Approved :: GNU Lesser General Public License v3 (LGPLv3)
Requires-Dist: odoo (<10.1dev,>=10.0)
